{
  "document_number": "02-10778",
  "publication_date": "2002-05-01",
  "title": "Revised Land and Resource Management Plan for the Ozark-St. Francis National Forests in Arkansas",
  "type": "Notice",
  "agency_names": null,
  "citation": "67 FR 21625",
  "html_url": "https://www.federalregister.gov/documents/2002/05/01/02-10778/revised-land-and-resource-management-plan-for-the-ozark-st-francis-national-forests-in-arkansas",
  "json_url": "https://www.federalregister.gov/api/v1/documents/02-10778?publication_date=2002-05-01",
  "raw_text_url": "https://www.federalregister.gov/documents/full_text/text/2002/05/01/02-10778.txt",
  "full_text_xml_url": "https://www.federalregister.gov/documents/full_text/xml/2002/05/01/02-10778.xml",
  "raw_saved": true,
  "xml_saved": true,
  "raw_status": "downloaded",
  "xml_status": "downloaded"
}