{
  "document_number": "E6-14736",
  "publication_date": "2006-09-07",
  "title": "Noninsured Crop Disaster Assistance Program-Tropical Regions",
  "type": "Rule",
  "agency_names": null,
  "citation": "71 FR 52738",
  "html_url": "https://www.federalregister.gov/documents/2006/09/07/E6-14736/noninsured-crop-disaster-assistance-program-tropical-regions",
  "json_url": "https://www.federalregister.gov/api/v1/documents/E6-14736?publication_date=2006-09-07",
  "raw_text_url": "https://www.federalregister.gov/documents/full_text/text/2006/09/07/E6-14736.txt",
  "full_text_xml_url": "https://www.federalregister.gov/documents/full_text/xml/2006/09/07/E6-14736.xml",
  "raw_saved": true,
  "xml_saved": true,
  "raw_status": "downloaded",
  "xml_status": "downloaded"
}