{
  "document_number": "2018-21197",
  "publication_date": "2018-09-28",
  "title": "Oil and Gas and Sulphur Operations on the Outer Continental Shelf-Oil and Gas Production Safety Systems",
  "type": "Rule",
  "agency_names": null,
  "citation": "83 FR 49216",
  "html_url": "https://www.federalregister.gov/documents/2018/09/28/2018-21197/oil-and-gas-and-sulphur-operations-on-the-outer-continental-shelf-oil-and-gas-production-safety",
  "json_url": "https://www.federalregister.gov/api/v1/documents/2018-21197?publication_date=2018-09-28",
  "raw_text_url": "https://www.federalregister.gov/documents/full_text/text/2018/09/28/2018-21197.txt",
  "full_text_xml_url": "https://www.federalregister.gov/documents/full_text/xml/2018/09/28/2018-21197.xml",
  "raw_saved": true,
  "xml_saved": true,
  "raw_status": "downloaded",
  "xml_status": "downloaded"
}