{
  "document_number": "2019-18607",
  "publication_date": "2019-08-30",
  "title": "Allocations, Common Application, Waivers, and Alternative Requirements for Community Development Block Grant Mitigation Grantees",
  "type": "Notice",
  "agency_names": null,
  "citation": "84 FR 45838",
  "html_url": "https://www.federalregister.gov/documents/2019/08/30/2019-18607/allocations-common-application-waivers-and-alternative-requirements-for-community-development-block",
  "json_url": "https://www.federalregister.gov/api/v1/documents/2019-18607?publication_date=2019-08-30",
  "raw_text_url": "https://www.federalregister.gov/documents/full_text/text/2019/08/30/2019-18607.txt",
  "full_text_xml_url": "https://www.federalregister.gov/documents/full_text/xml/2019/08/30/2019-18607.xml",
  "raw_saved": true,
  "xml_saved": true,
  "raw_status": "downloaded",
  "xml_status": "downloaded"
}