{
  "document_number": "2014-04861",
  "publication_date": "2014-03-05",
  "title": "National Advisory Council",
  "type": "Notice",
  "agency_names": null,
  "citation": "79 FR 12518",
  "html_url": "https://www.federalregister.gov/documents/2014/03/05/2014-04861/national-advisory-council",
  "json_url": "https://www.federalregister.gov/api/v1/documents/2014-04861?publication_date=2014-03-05",
  "raw_text_url": "https://www.federalregister.gov/documents/full_text/text/2014/03/05/2014-04861.txt",
  "full_text_xml_url": "https://www.federalregister.gov/documents/full_text/xml/2014/03/05/2014-04861.xml",
  "raw_saved": true,
  "xml_saved": true,
  "raw_status": "downloaded",
  "xml_status": "downloaded"
}