{
  "document_number": "2013-21244",
  "publication_date": "2013-08-30",
  "title": "Agency Information Collection Activities: Submission for OMB Review; Comment Request",
  "type": "Notice",
  "agency_names": null,
  "citation": "78 FR 53774",
  "html_url": "https://www.federalregister.gov/documents/2013/08/30/2013-21244/agency-information-collection-activities-submission-for-omb-review-comment-request",
  "json_url": "https://www.federalregister.gov/api/v1/documents/2013-21244?publication_date=2013-08-30",
  "raw_text_url": "https://www.federalregister.gov/documents/full_text/text/2013/08/30/2013-21244.txt",
  "full_text_xml_url": "https://www.federalregister.gov/documents/full_text/xml/2013/08/30/2013-21244.xml",
  "raw_saved": true,
  "xml_saved": true,
  "raw_status": "downloaded",
  "xml_status": "downloaded"
}