{
  "document_number": "E9-30891",
  "publication_date": "2010-01-08",
  "title": "Energy Conservation Program: Energy Conservation Standards for Certain Consumer Products (Dishwashers, Dehumidifiers, Microwave Ovens, and Electric and Gas Kitchen Ranges and Ovens) and for Certain Commercial and Industrial Equipment (Commercial Clothes Washers)",
  "type": "Rule",
  "agency_names": null,
  "citation": "75 FR 1122",
  "html_url": "https://www.federalregister.gov/documents/2010/01/08/E9-30891/energy-conservation-program-energy-conservation-standards-for-certain-consumer-products-dishwashers",
  "json_url": "https://www.federalregister.gov/api/v1/documents/E9-30891?publication_date=2010-01-08",
  "raw_text_url": "https://www.federalregister.gov/documents/full_text/text/2010/01/08/E9-30891.txt",
  "full_text_xml_url": "https://www.federalregister.gov/documents/full_text/xml/2010/01/08/E9-30891.xml",
  "raw_saved": true,
  "xml_saved": true,
  "raw_status": "downloaded",
  "xml_status": "downloaded"
}