{
  "document_number": "2024-27981",
  "publication_date": "2024-12-05",
  "title": "Establishing Reasonable Period of Time and Clarifications Regarding Clean Water Act Section 401(a)(1) Certifications for Hydroelectric Proceedings",
  "type": "Rule",
  "agency_names": null,
  "citation": "89 FR 96524",
  "html_url": "https://www.federalregister.gov/documents/2024/12/05/2024-27981/establishing-reasonable-period-of-time-and-clarifications-regarding-clean-water-act-section-401a1",
  "json_url": "https://www.federalregister.gov/api/v1/documents/2024-27981?publication_date=2024-12-05",
  "raw_text_url": "https://www.federalregister.gov/documents/full_text/text/2024/12/05/2024-27981.txt",
  "full_text_xml_url": "https://www.federalregister.gov/documents/full_text/xml/2024/12/05/2024-27981.xml",
  "raw_saved": true,
  "xml_saved": true,
  "raw_status": "downloaded",
  "xml_status": "downloaded"
}