{
  "document_number": "E9-29070",
  "publication_date": "2009-12-08",
  "title": "Agricultural Management Assistance Program",
  "type": "Rule",
  "agency_names": null,
  "citation": "74 FR 64591",
  "html_url": "https://www.federalregister.gov/documents/2009/12/08/E9-29070/agricultural-management-assistance-program",
  "json_url": "https://www.federalregister.gov/api/v1/documents/E9-29070?publication_date=2009-12-08",
  "raw_text_url": "https://www.federalregister.gov/documents/full_text/text/2009/12/08/E9-29070.txt",
  "full_text_xml_url": "https://www.federalregister.gov/documents/full_text/xml/2009/12/08/E9-29070.xml",
  "raw_saved": true,
  "xml_saved": true,
  "raw_status": "downloaded",
  "xml_status": "downloaded"
}