{
  "document_number": "2020-05900",
  "publication_date": "2020-07-07",
  "title": "National Emission Standards for Hazardous Air Pollutants: Organic Liquids Distribution (Non-Gasoline) Residual Risk and Technology Review",
  "type": "Rule",
  "agency_names": null,
  "citation": "85 FR 40740",
  "html_url": "https://www.federalregister.gov/documents/2020/07/07/2020-05900/national-emission-standards-for-hazardous-air-pollutants-organic-liquids-distribution-non-gasoline",
  "json_url": "https://www.federalregister.gov/api/v1/documents/2020-05900?publication_date=2020-07-07",
  "raw_text_url": "https://www.federalregister.gov/documents/full_text/text/2020/07/07/2020-05900.txt",
  "full_text_xml_url": "https://www.federalregister.gov/documents/full_text/xml/2020/07/07/2020-05900.xml",
  "raw_saved": true,
  "xml_saved": true,
  "raw_status": "downloaded",
  "xml_status": "downloaded"
}